README.md
mdx_unimoji.py
setup.py
mdx_unimoji.egg-info/PKG-INFO
mdx_unimoji.egg-info/SOURCES.txt
mdx_unimoji.egg-info/dependency_links.txt
mdx_unimoji.egg-info/requires.txt
mdx_unimoji.egg-info/top_level.txt