Metadata-Version: 1.1
Name: mdx-unimoji
Version: 1.0
Summary: Python-Markdown extension that replaces common smileys with their Unicode emoji emoticons. ;)
Home-page: https://github.com/kernc/mdx_unimoji
Author: Jack Nicholson
Author-email: kern.ce.ce++@gmail.com
License: GPLv3+
Keywords: markdown unicode emoji emoticon
Platform: UNKNOWN
Classifier: Development Status :: 5 - Production/Stable
Classifier: Operating System :: OS Independent
Classifier: License :: OSI Approved :: GNU General Public License v3 or later (GPLv3+)
Classifier: Environment :: Web Environment
Classifier: Programming Language :: Python :: 2.7
Classifier: Programming Language :: Python :: 3
Classifier: Topic :: Internet :: WWW/HTTP :: Dynamic Content :: Message Boards
Classifier: Topic :: Internet :: WWW/HTTP :: Dynamic Content :: News/Diary
Classifier: Topic :: Text Processing :: Filters
Classifier: Topic :: Text Processing :: Markup :: HTML
